spydir.py
spydir-0.1.2.dist-info/LICENSE
spydir-0.1.2.dist-info/METADATA
spydir-0.1.2.dist-info/WHEEL
spydir-0.1.2.dist-info/entry_points.txt
spydir-0.1.2.dist-info/top_level.txt
spydir-0.1.2.dist-info/RECORD
