Metadata-Version: 2.1
Name: spydir
Version: 0.1.2
Author: Sergey M
License: FUCK LICENSE
Project-URL: Repository, https://github.com/s3rgeym/spydir.git
Classifier: Topic :: Internet
Requires-Python: >=3.11.7
License-File: LICENSE
Requires-Dist: requests
Provides-Extra: dev
Requires-Dist: black ; extra == 'dev'
Requires-Dist: pylint ; extra == 'dev'
Provides-Extra: test
Requires-Dist: pytest ; extra == 'test'
